file_handler/__init__.py
file_handler/file_converter.py
file_handler/file_reader.py
file_handler/file_writer.py
file_handler_armaan-0.3.dist-info/METADATA
file_handler_armaan-0.3.dist-info/WHEEL
file_handler_armaan-0.3.dist-info/top_level.txt
file_handler_armaan-0.3.dist-info/RECORD
